azure/data/tables/__init__.py
azure/data/tables/_authentication.py
azure/data/tables/_base_client.py
azure/data/tables/_common_conversion.py
azure/data/tables/_constants.py
azure/data/tables/_deserialize.py
azure/data/tables/_entity.py
azure/data/tables/_error.py
azure/data/tables/_models.py
azure/data/tables/_policies.py
azure/data/tables/_sdk_moniker.py
azure/data/tables/_serialize.py
azure/data/tables/_shared_access_signature.py
azure/data/tables/_table_batch.py
azure/data/tables/_table_client.py
azure/data/tables/_table_service_client.py
azure/data/tables/_table_shared_access_signature.py
azure/data/tables/_version.py
azure/data/tables/py.typed
azure/data/tables/_generated/__init__.py
azure/data/tables/_generated/_client.py
azure/data/tables/_generated/_configuration.py
azure/data/tables/_generated/_patch.py
azure/data/tables/_generated/_serialization.py
azure/data/tables/_generated/_vendor.py
azure/data/tables/_generated/_version.py
azure/data/tables/_generated/py.typed
azure/data/tables/_generated/aio/__init__.py
azure/data/tables/_generated/aio/_client.py
azure/data/tables/_generated/aio/_configuration.py
azure/data/tables/_generated/aio/_patch.py
azure/data/tables/_generated/aio/operations/__init__.py
azure/data/tables/_generated/aio/operations/_operations.py
azure/data/tables/_generated/aio/operations/_patch.py
azure/data/tables/_generated/models/__init__.py
azure/data/tables/_generated/models/_enums.py
azure/data/tables/_generated/models/_models.py
azure/data/tables/_generated/models/_patch.py
azure/data/tables/_generated/operations/__init__.py
azure/data/tables/_generated/operations/_operations.py
azure/data/tables/_generated/operations/_patch.py
azure/data/tables/aio/__init__.py
azure/data/tables/aio/_authentication_async.py
azure/data/tables/aio/_base_client_async.py
azure/data/tables/aio/_models.py
azure/data/tables/aio/_policies_async.py
azure/data/tables/aio/_table_client_async.py
azure/data/tables/aio/_table_service_client_async.py
azure_data_tables-12.5.0.dist-info/LICENSE
azure_data_tables-12.5.0.dist-info/METADATA
azure_data_tables-12.5.0.dist-info/WHEEL
azure_data_tables-12.5.0.dist-info/top_level.txt
azure_data_tables-12.5.0.dist-info/RECORD
