Metadata-Version: 2.1
Name: azure-data-tables
Version: 12.5.0
Summary: Microsoft Azure Azure Data Tables Client Library for Python
Home-page: https://github.com/Azure/azure-sdk-for-python/tree/main/sdk/table/azure-table
Author: Microsoft Corporation
Author-email: ascl@microsoft.com
License: MIT License
Keywords: azure,azure sdk
Classifier: Development Status :: 5 - Production/Stable
Classifier: Programming Language :: Python
Classifier: Programming Language :: Python :: 3 :: Only
Classifier: Programming Language :: Python :: 3
Classifier: Programming Language :: Python :: 3.8
Classifier: Programming Language :: Python :: 3.9
Classifier: Programming Language :: Python :: 3.10
Classifier: Programming Language :: Python :: 3.11
Classifier: Programming Language :: Python :: 3.12
Classifier: License :: OSI Approved :: MIT License
Requires-Python: >=3.8
License-File: LICENSE
Requires-Dist: azure-core<2.0.0,>=1.29.4
Requires-Dist: yarl<2.0,>=1.0
Requires-Dist: isodate<1.0.0,>=0.6.1
Requires-Dist: typing-extensions>=4.3.0
